network_cards/__init__.py
network_cards/format_helpers.py
network_cards/network_cards.py
network_cards-0.99.2.2.dist-info/LICENSE
network_cards-0.99.2.2.dist-info/METADATA
network_cards-0.99.2.2.dist-info/WHEEL
network_cards-0.99.2.2.dist-info/RECORD
