Metadata-Version: 2.1
Name: network-cards
Version: 0.99.2.2
Summary: Concise, readable summaries of network data
License: BSD-3-Clause
Author: James Bagrow
Requires-Python: >=3.8,<4.0
Classifier: License :: OSI Approved :: BSD License
Classifier: Programming Language :: Python :: 3
Classifier: Programming Language :: Python :: 3.8
Classifier: Programming Language :: Python :: 3.9
Classifier: Programming Language :: Python :: 3.10
Classifier: Programming Language :: Python :: 3.11
Requires-Dist: networkx (>=2.8.2,<3.0.0)
Requires-Dist: pandas (>=1.4.2,<2.0.0)
